billingflatfile.py
billingflatfile-1.0.6.dist-info/LICENSE
billingflatfile-1.0.6.dist-info/METADATA
billingflatfile-1.0.6.dist-info/WHEEL
billingflatfile-1.0.6.dist-info/top_level.txt
billingflatfile-1.0.6.dist-info/RECORD
