Metadata-Version: 2.1
Name: billingflatfile
Version: 1.0.6
Summary: Generate the required fixed width format files from delimited files extracts for EMR billing purposes
Home-page: https://github.com/e2jk/billingflatfile
Author: Emilien Klein
Author-email: emilien@klein.st
License: UNKNOWN
Platform: UNKNOWN
Classifier: Programming Language :: Python :: 3
Classifier: License :: OSI Approved :: MIT License
Classifier: Operating System :: OS Independent
Requires-Python: >=3.6
Requires-Dist: delimited2fixedwidth (==1.0.11)
Requires-Dist: et-xmlfile (==1.1.0) ; python_version >= "3.6"
Requires-Dist: openpyxl (==3.0.7) ; python_version >= "3.6"
